omlish/.omlish-manifests.json
omlish/CODESTYLE.md
omlish/README.md
omlish/__about__.py
omlish/__init__.py
omlish/_check.cc
omlish/c3.py
omlish/cached.py
omlish/check.py
omlish/datetimes.py
omlish/libc.py
omlish/metadata.py
omlish/runmodule.py
omlish/shlex.py
omlish/algorithm/__init__.py
omlish/algorithm/all.py
omlish/algorithm/distribute.py
omlish/algorithm/toposort.py
omlish/algorithm/unify.py
omlish/argparse/__init__.py
omlish/argparse/all.py
omlish/argparse/cli.py
omlish/argparse/utils.py
omlish/asyncs/__init__.py
omlish/asyncs/buffers.py
omlish/asyncs/sync.py
omlish/asyncs/trio_asyncio.py
omlish/asyncs/anyio/__init__.py
omlish/asyncs/anyio/backends.py
omlish/asyncs/anyio/futures.py
omlish/asyncs/anyio/signals.py
omlish/asyncs/anyio/streams.py
omlish/asyncs/anyio/subprocesses.py
omlish/asyncs/anyio/sync.py
omlish/asyncs/anyio/utils.py
omlish/asyncs/asyncio/__init__.py
omlish/asyncs/asyncio/all.py
omlish/asyncs/asyncio/channels.py
omlish/asyncs/asyncio/rlock.py
omlish/asyncs/asyncio/sockets.py
omlish/asyncs/asyncio/streams.py
omlish/asyncs/asyncio/subprocesses.py
omlish/asyncs/asyncio/sync.py
omlish/asyncs/asyncio/timeouts.py
omlish/asyncs/asyncio/utils.py
omlish/asyncs/asynclite/README.md
omlish/asyncs/asynclite/__init__.py
omlish/asyncs/asynclite/all.py
omlish/asyncs/asynclite/api.py
omlish/asyncs/asynclite/base.py
omlish/asyncs/asynclite/events.py
omlish/asyncs/asynclite/identities.py
omlish/asyncs/asynclite/locks.py
omlish/asyncs/asynclite/queues.py
omlish/asyncs/asynclite/semaphores.py
omlish/asyncs/asynclite/sleeps.py
omlish/asyncs/asynclite/anyio/__init__.py
omlish/asyncs/asynclite/anyio/all.py
omlish/asyncs/asynclite/anyio/api.py
omlish/asyncs/asynclite/anyio/base.py
omlish/asyncs/asynclite/anyio/events.py
omlish/asyncs/asynclite/anyio/identities.py
omlish/asyncs/asynclite/anyio/locks.py
omlish/asyncs/asynclite/anyio/queues.py
omlish/asyncs/asynclite/anyio/semaphores.py
omlish/asyncs/asynclite/anyio/sleeps.py
omlish/asyncs/asynclite/asyncio/__init__.py
omlish-0.0.0.dev516.dist-info/licenses/LICENSE
omlish-0.0.0.dev516.dist-info/METADATA
omlish-0.0.0.dev516.dist-info/WHEEL
omlish-0.0.0.dev516.dist-info/entry_points.txt
omlish-0.0.0.dev516.dist-info/top_level.txt
omlish-0.0.0.dev516.dist-info/RECORD
