Metadata-Version: 2.4
Name: omlish
Version: 0.0.0.dev516
Summary: omlish
Author: wrmsr
License-Expression: BSD-3-Clause
Project-URL: source, https://github.com/wrmsr/omlish
Classifier: Development Status :: 2 - Pre-Alpha
Classifier: Intended Audience :: Developers
Classifier: Operating System :: OS Independent
Classifier: Operating System :: POSIX
Classifier: Programming Language :: Python :: 3
Classifier: Programming Language :: Python :: 3.13
Requires-Python: >=3.13
License-File: LICENSE
Provides-Extra: all
Requires-Dist: anyio~=4.11; extra == "all"
Requires-Dist: sniffio~=1.3; extra == "all"
Requires-Dist: greenlet~=3.3; extra == "all"
Requires-Dist: trio~=0.32; extra == "all"
Requires-Dist: trio-asyncio~=0.15; extra == "all"
Requires-Dist: lz4~=4.4; extra == "all"
Requires-Dist: python-snappy~=0.7; extra == "all"
Requires-Dist: zstandard~=0.25; python_version < "3.14" and extra == "all"
Requires-Dist: brotli~=1.2; extra == "all"
Requires-Dist: asttokens~=3.0; extra == "all"
Requires-Dist: executing~=2.2; extra == "all"
Requires-Dist: psutil~=7.2; extra == "all"
Requires-Dist: orjson~=3.11; extra == "all"
Requires-Dist: ujson~=5.11; extra == "all"
Requires-Dist: pyyaml~=6.0; extra == "all"
Requires-Dist: cbor2~=5.8; extra == "all"
Requires-Dist: cloudpickle~=3.1; extra == "all"
Requires-Dist: httpx[http2]~=0.28; extra == "all"
Requires-Dist: wrapt~=2.0; extra == "all"
Requires-Dist: cryptography~=46.0; extra == "all"
Requires-Dist: sqlalchemy[asyncio]~=2.0; extra == "all"
Requires-Dist: pg8000~=1.31; extra == "all"
Requires-Dist: pymysql~=1.1; extra == "all"
Requires-Dist: snowflake-connector-python~=4.2; extra == "all"
Requires-Dist: aiomysql~=0.3; extra == "all"
Requires-Dist: aiosqlite~=0.22; extra == "all"
Requires-Dist: asyncpg~=0.31; extra == "all"
Requires-Dist: apsw~=3.51; extra == "all"
Requires-Dist: sqlean.py~=3.50; extra == "all"
Requires-Dist: duckdb~=1.4; extra == "all"
Requires-Dist: markupsafe~=3.0; extra == "all"
Requires-Dist: jinja2~=3.1; extra == "all"
Requires-Dist: pytest~=9.0; extra == "all"
Requires-Dist: anyio~=4.11; extra == "all"
Requires-Dist: sniffio~=1.3; extra == "all"
Requires-Dist: asttokens~=3.0; extra == "all"
Requires-Dist: executing~=2.2; extra == "all"
Requires-Dist: orjson~=3.11; extra == "all"
Requires-Dist: pyyaml~=6.0; extra == "all"
Requires-Dist: wrapt~=2.0; extra == "all"
Provides-Extra: async
Requires-Dist: anyio~=4.11; extra == "async"
Requires-Dist: sniffio~=1.3; extra == "async"
Requires-Dist: greenlet~=3.3; extra == "async"
Requires-Dist: trio~=0.32; extra == "async"
Requires-Dist: trio-asyncio~=0.15; extra == "async"
Provides-Extra: compress
Requires-Dist: lz4~=4.4; extra == "compress"
Requires-Dist: python-snappy~=0.7; extra == "compress"
Requires-Dist: zstandard~=0.25; python_version < "3.14" and extra == "compress"
Requires-Dist: brotli~=1.2; extra == "compress"
Provides-Extra: diag
Requires-Dist: asttokens~=3.0; extra == "diag"
Requires-Dist: executing~=2.2; extra == "diag"
Requires-Dist: psutil~=7.2; extra == "diag"
Provides-Extra: formats
Requires-Dist: orjson~=3.11; extra == "formats"
Requires-Dist: ujson~=5.11; extra == "formats"
Requires-Dist: pyyaml~=6.0; extra == "formats"
Requires-Dist: cbor2~=5.8; extra == "formats"
Requires-Dist: cloudpickle~=3.1; extra == "formats"
Provides-Extra: http
Requires-Dist: httpx[http2]~=0.28; extra == "http"
Provides-Extra: misc
Requires-Dist: wrapt~=2.0; extra == "misc"
Provides-Extra: secrets
Requires-Dist: cryptography~=46.0; extra == "secrets"
Provides-Extra: sqlalchemy
Requires-Dist: sqlalchemy[asyncio]~=2.0; extra == "sqlalchemy"
Provides-Extra: sqldrivers
Requires-Dist: pg8000~=1.31; extra == "sqldrivers"
Requires-Dist: pymysql~=1.1; extra == "sqldrivers"
Requires-Dist: snowflake-connector-python~=4.2; extra == "sqldrivers"
Requires-Dist: aiomysql~=0.3; extra == "sqldrivers"
Requires-Dist: aiosqlite~=0.22; extra == "sqldrivers"
Requires-Dist: asyncpg~=0.31; extra == "sqldrivers"
Requires-Dist: apsw~=3.51; extra == "sqldrivers"
Requires-Dist: sqlean.py~=3.50; extra == "sqldrivers"
Requires-Dist: duckdb~=1.4; extra == "sqldrivers"
Provides-Extra: templates
Requires-Dist: markupsafe~=3.0; extra == "templates"
Requires-Dist: jinja2~=3.1; extra == "templates"
Provides-Extra: testing
Requires-Dist: pytest~=9.0; extra == "testing"
Provides-Extra: plus
Requires-Dist: anyio~=4.11; extra == "plus"
Requires-Dist: sniffio~=1.3; extra == "plus"
Requires-Dist: asttokens~=3.0; extra == "plus"
Requires-Dist: executing~=2.2; extra == "plus"
Requires-Dist: orjson~=3.11; extra == "plus"
Requires-Dist: pyyaml~=6.0; extra == "plus"
Requires-Dist: wrapt~=2.0; extra == "plus"
Dynamic: license-file
